configstruct/__init__.py
configstruct/config_struct.py
configstruct/open_struct.py
configstruct/section_struct.py
configstruct-0.3.1.dist-info/DESCRIPTION.rst
configstruct-0.3.1.dist-info/METADATA
configstruct-0.3.1.dist-info/RECORD
configstruct-0.3.1.dist-info/WHEEL
configstruct-0.3.1.dist-info/metadata.json
configstruct-0.3.1.dist-info/top_level.txt
