Metadata-Version: 2.0
Name: configstruct
Version: 0.3.1
Summary: Simplified configuration and settings management library.
Home-page: https://github.com/bradrf/configstruct
Author: Brad Robel-Forrest
Author-email: brad@bitpony.com
License: MIT license
Keywords: configstruct
Platform: UNKNOWN
Classifier: Development Status :: 2 - Pre-Alpha
Classifier: Intended Audience :: Developers
Classifier: License :: OSI Approved :: MIT License
Classifier: Natural Language :: English
Classifier: Programming Language :: Python :: 2
Classifier: Programming Language :: Python :: 2.6
Classifier: Programming Language :: Python :: 2.7
Classifier: Programming Language :: Python :: 3
Classifier: Programming Language :: Python :: 3.3
Classifier: Programming Language :: Python :: 3.4
Classifier: Programming Language :: Python :: 3.5
Requires-Dist: configparser (>=3.5.0)
Requires-Dist: future (>=0.16.0)
